alma_cdk/project/__init__.py
alma_cdk/project/py.typed
alma_cdk/project/_jsii/__init__.py
alma_cdk/project/_jsii/project@1.0.9.jsii.tgz
alma_cdk.project-1.0.9.dist-info/LICENSE
alma_cdk.project-1.0.9.dist-info/METADATA
alma_cdk.project-1.0.9.dist-info/WHEEL
alma_cdk.project-1.0.9.dist-info/top_level.txt
alma_cdk.project-1.0.9.dist-info/RECORD
